pydatascraper/init.py
pydatascraper/pyscraper.py
pydatascraper-1.0.4.dist-info/LICENSE
pydatascraper-1.0.4.dist-info/METADATA
pydatascraper-1.0.4.dist-info/WHEEL
pydatascraper-1.0.4.dist-info/top_level.txt
pydatascraper-1.0.4.dist-info/RECORD
